fastapi_redis/__init__.py
fastapi_redis/fastapi_redis.py
fastapi_redis/types.py
fastapi_redis/tests/__init__.py
fastapi_redis/tests/test.py
fastapi_redis/utils/__init__.py
fastapi_redis/utils/singleton.py
fastapi_redis_vet1ments-0.2.6.dist-info/METADATA
fastapi_redis_vet1ments-0.2.6.dist-info/WHEEL
fastapi_redis_vet1ments-0.2.6.dist-info/top_level.txt
fastapi_redis_vet1ments-0.2.6.dist-info/RECORD
