Metadata-Version: 2.1
Name: fastapi-redis-vet1ments
Version: 0.2.6
Summary: redis 쉽게
Author: no hong seok
Author-email: vet1ments@naver.com
Maintainer: no hong seok
Maintainer-email: vet1ments@naver.com
License: MIT
Project-URL: Repository, https://github.com/vet1ments/fastapi_redis
Requires-Python: >=3.11.0
Requires-Dist: redis[hiredis] >=5.0.0
Requires-Dist: fastapi[all] >=0.111.0
